lcdp_fastapi_utils/__init__.py
lcdp_fastapi_utils/background_task.py
lcdp_fastapi_utils-1.5.9.dist-info/METADATA
lcdp_fastapi_utils-1.5.9.dist-info/WHEEL
lcdp_fastapi_utils-1.5.9.dist-info/RECORD
