Metadata-Version: 2.4
Name: lcdp-fastapi-utils
Version: 1.5.9
Summary: FastApi Utils
Author: Le Comptoir Des Pharmacies
Author-email: webmaster@lecomptoirdespharmacies.fr
Requires-Python: >=3.12
Classifier: Programming Language :: Python :: 3
Classifier: Programming Language :: Python :: 3.12
Classifier: Programming Language :: Python :: 3.13
Classifier: Programming Language :: Python :: 3.14
Requires-Dist: uvicorn (==0.34.2)
